loghelper/__init__.py
loghelper/loghelper.py
loghelper/ver.py
loghelper-1.0.9.dist-info/METADATA
loghelper-1.0.9.dist-info/WHEEL
loghelper-1.0.9.dist-info/RECORD
