Metadata-Version: 2.1
Name: loghelper
Version: 1.0.9
Summary: 日志助手，支持多进程，支持json格式，支持flask
Author: ITXiaoPang
Author-email: itxiaopang.djh@gmail.com
Requires-Python: >=3.8,<4.0
Classifier: Programming Language :: Python :: 3
Classifier: Programming Language :: Python :: 3.8
Classifier: Programming Language :: Python :: 3.9
Classifier: Programming Language :: Python :: 3.10
Classifier: Programming Language :: Python :: 3.11
Provides-Extra: concurrent
Provides-Extra: flask
Provides-Extra: json
Requires-Dist: Flask (>=2.0,<3.0) ; extra == "flask"
Requires-Dist: concurrent-log (>=1.0,<2.0) ; extra == "concurrent"
Requires-Dist: python-json-logger (>=2.0,<3.0) ; extra == "json"
